poetry_ycf_plugin/__init__.py
poetry_ycf_plugin/commands.py
poetry_ycf_plugin/config.py
poetry_ycf_plugin/deploy_manager.py
poetry_ycf_plugin/exceptions.py
poetry_ycf_plugin/plugins.py
poetry_ycf_plugin/responses.py
poetry_ycf_plugin/utils.py
poetry_ycf_plugin-0.2.0.dist-info/METADATA
poetry_ycf_plugin-0.2.0.dist-info/WHEEL
poetry_ycf_plugin-0.2.0.dist-info/entry_points.txt
poetry_ycf_plugin-0.2.0.dist-info/top_level.txt
poetry_ycf_plugin-0.2.0.dist-info/RECORD
