Metadata-Version: 2.1
Name: poetry-ycf-plugin
Version: 0.2.0
Summary: Poetry plugin for working with Yandex Cloud Functions
Author-email: Aleksei Marusich <aleksei.marusich@rocshers.com>
License: MIT
Project-URL: Homepage, https://projects.rocshers.com/open-source/poetry-ycf-plugin
Project-URL: Repository, https://gitlab.com/rocshers/python/poetry-ycf-plugin
Keywords: rocshers,poetry,git
Classifier: License :: OSI Approved :: MIT License
Classifier: Intended Audience :: Developers
Classifier: Intended Audience :: Information Technology
Classifier: Intended Audience :: System Administrators
Classifier: Topic :: Software Development :: Libraries :: Python Modules
Classifier: Topic :: Software Development :: Libraries
Classifier: Topic :: Software Development
Classifier: Topic :: System :: Installation/Setup
Classifier: Topic :: System :: Software Distribution
Classifier: Programming Language :: Python
Classifier: Programming Language :: Python :: 3
Classifier: Programming Language :: Python :: 3.12
Classifier: Programming Language :: Python :: 3 :: Only
Requires-Python: >=3.12
Requires-Dist: boto3>=1.35.84
Requires-Dist: poetry>=1.6
Requires-Dist: poetry-plugin-export>=1.3.1
Requires-Dist: pydantic>=2.7.0
Requires-Dist: pydantic-settings>=2.3.0
Requires-Dist: pyjwt>=2.10.1
